{
  "routeId": 935,
  "territoryId": 958,
  "zoneName": "Garlemald",
  "placeName": "Regio Urbanissima",
  "expansionId": 4,
  "gatheringJobId": 17,
  "levelRequirement": 90,
  "nodeIds": [
    34433
  ],
  "nodeInfo": [
    {
      "groupId": 0,
      "nodeId": 34433,
      "locations": [
        {
          "position": {
            "x": -168.1372,
            "y": 11.92413,
            "z": -480.7224
          },
          "allowFlying": true,
          "flight_FanInfo": {
            "fan_StartAngle": 0,
            "fan_EndAngle": 359,
            "fan_DistanceMin": 2.5,
            "fan_DistanceMax": 4,
            "fan_Height": 0
          },
          "gathering_FanInfo": {
            "fan_StartAngle": 0,
            "fan_EndAngle": 359,
            "fan_DistanceMin": 1,
            "fan_DistanceMax": 2,
            "fan_Height": 0
          },
          "useSpecificWalkingSpots": false,
          "walkablePositions": []
        },
        {
          "position": {
            "x": -174.0028,
            "y": 11.9945,
            "z": -435.036
          },
          "allowFlying": true,
          "flight_FanInfo": {
            "fan_StartAngle": 33,
            "fan_EndAngle": 178,
            "fan_DistanceMin": 2.5,
            "fan_DistanceMax": 4,
            "fan_Height": 0
          },
          "gathering_FanInfo": {
            "fan_StartAngle": 0,
            "fan_EndAngle": 359,
            "fan_DistanceMin": 1,
            "fan_DistanceMax": 2,
            "fan_Height": 0
          },
          "useSpecificWalkingSpots": false,
          "walkablePositions": []
        },
        {
          "position": {
            "x": -214.9574,
            "y": 12.07928,
            "z": -434.5291
          },
          "allowFlying": true,
          "flight_FanInfo": {
            "fan_StartAngle": 0,
            "fan_EndAngle": 359,
            "fan_DistanceMin": 2.2,
            "fan_DistanceMax": 3.2,
            "fan_Height": 0
          },
          "gathering_FanInfo": {
            "fan_StartAngle": 0,
            "fan_EndAngle": 359,
            "fan_DistanceMin": 1,
            "fan_DistanceMax": 2,
            "fan_Height": 0
          },
          "useSpecificWalkingSpots": false,
          "walkablePositions": []
        }
      ]
    }
  ],
  "groupCount": 1,
  "requiresFolklore": false,
  "folkloreBook": "",
  "author": "alydev",
  "lastUpdated": "2025-12-29 16:30:40",
  "timedNode": false
}