{
  "routeId": 222,
  "territoryId": 155,
  "zoneName": "Coerthas Central Highlands",
  "placeName": "Dragonhead",
  "expansionId": 0,
  "gatheringJobId": 16,
  "levelRequirement": 50,
  "nodeIds": [
    31010
  ],
  "requiresFolklore": false,
  "folkloreBook": "",
  "author": "alydev",
  "lastUpdated": "2025-12-08",
  "nodeGroups": [
    {
      "groupId": 0,
      "nodes": [
        {
          "nodeId": 31010,
          "locations": [
            {
              "position": {
                "x": 297.1792,
                "y": 308.5222,
                "z": -95.92535
              },
              "minAngle": 50,
              "maxAngle": 75,
              "minDistance": 1,
              "maxDistance": 5,
              "fanHightIncrease": 0,
              "allowFlying": true,
              "specificWalkSpots": false,
              "walkablePositions": [],
              "gatherAngle_Minimum": 0,
              "gatherAngle_Maximum": 0,
              "gatherDistance_Minimum": 1,
              "gatherDistance_Maximum": 2.4,
              "gatherFan_Height": 0
            },
            {
              "position": {
                "x": 306.2995,
                "y": 307.3925,
                "z": -55.46556
              },
              "minAngle": 85,
              "maxAngle": 115,
              "minDistance": 1,
              "maxDistance": 5,
              "fanHightIncrease": 0,
              "allowFlying": true,
              "specificWalkSpots": false,
              "walkablePositions": [],
              "gatherAngle_Minimum": 0,
              "gatherAngle_Maximum": 0,
              "gatherDistance_Minimum": 1,
              "gatherDistance_Maximum": 2.4,
              "gatherFan_Height": 0
            },
            {
              "position": {
                "x": 310.0573,
                "y": 309.8751,
                "z": -80.9975
              },
              "minAngle": 25,
              "maxAngle": 85,
              "minDistance": 1,
              "maxDistance": 5,
              "fanHightIncrease": 0,
              "allowFlying": true,
              "specificWalkSpots": false,
              "walkablePositions": [],
              "gatherAngle_Minimum": 0,
              "gatherAngle_Maximum": 0,
              "gatherDistance_Minimum": 1,
              "gatherDistance_Maximum": 2.4,
              "gatherFan_Height": 0
            }
          ]
        }
      ]
    }
  ],
  "timedNode": false
}