{
  "routeId": 638,
  "territoryId": 816,
  "zoneName": "Il Mheg",
  "placeName": "North Lyhe Ghiah",
  "expansionId": 3,
  "gatheringJobId": 18,
  "levelRequirement": 0,
  "nodeIds": [
    32783,
    32784,
    32785
  ],
  "nodeInfo": [
    {
      "groupId": 0,
      "nodeId": 32785,
      "locations": [
        {
          "position": {
            "x": -51.16975,
            "y": -65.91542,
            "z": -331.8114
          },
          "allowFlying": true,
          "flight_FanInfo": {
            "fan_StartAngle": 0,
            "fan_EndAngle": 359,
            "fan_DistanceMin": 1,
            "fan_DistanceMax": 2,
            "fan_Height": 0
          },
          "gathering_FanInfo": {
            "fan_StartAngle": 0,
            "fan_EndAngle": 359,
            "fan_DistanceMin": 1,
            "fan_DistanceMax": 2,
            "fan_Height": 0
          },
          "useSpecificWalkingSpots": false,
          "walkablePositions": []
        },
        {
          "position": {
            "x": -62.72931,
            "y": -64.74178,
            "z": -338.1311
          },
          "allowFlying": true,
          "flight_FanInfo": {
            "fan_StartAngle": 0,
            "fan_EndAngle": 359,
            "fan_DistanceMin": 1,
            "fan_DistanceMax": 2,
            "fan_Height": 0
          },
          "gathering_FanInfo": {
            "fan_StartAngle": 0,
            "fan_EndAngle": 359,
            "fan_DistanceMin": 1,
            "fan_DistanceMax": 2,
            "fan_Height": 0
          },
          "useSpecificWalkingSpots": false,
          "walkablePositions": []
        }
      ]
    },
    {
      "groupId": 1,
      "nodeId": 32784,
      "locations": [
        {
          "position": {
            "x": 4.685949,
            "y": -41.08909,
            "z": -439.1694
          },
          "allowFlying": true,
          "flight_FanInfo": {
            "fan_StartAngle": 96,
            "fan_EndAngle": 335,
            "fan_DistanceMin": 1,
            "fan_DistanceMax": 2,
            "fan_Height": 0
          },
          "gathering_FanInfo": {
            "fan_StartAngle": 96,
            "fan_EndAngle": 335,
            "fan_DistanceMin": 1,
            "fan_DistanceMax": 2,
            "fan_Height": 0
          },
          "useSpecificWalkingSpots": false,
          "walkablePositions": []
        },
        {
          "position": {
            "x": 0.8481219,
            "y": -40.92548,
            "z": -455.4055
          },
          "allowFlying": true,
          "flight_FanInfo": {
            "fan_StartAngle": 167,
            "fan_EndAngle": 47,
            "fan_DistanceMin": 1,
            "fan_DistanceMax": 2,
            "fan_Height": 0
          },
          "gathering_FanInfo": {
            "fan_StartAngle": 167,
            "fan_EndAngle": 47,
            "fan_DistanceMin": 1,
            "fan_DistanceMax": 2,
            "fan_Height": 0
          },
          "useSpecificWalkingSpots": false,
          "walkablePositions": []
        }
      ]
    },
    {
      "groupId": 2,
      "nodeId": 32783,
      "locations": [
        {
          "position": {
            "x": -152.6249,
            "y": -49.67373,
            "z": -464.8353
          },
          "allowFlying": true,
          "flight_FanInfo": {
            "fan_StartAngle": 0,
            "fan_EndAngle": 0,
            "fan_DistanceMin": 1,
            "fan_DistanceMax": 3,
            "fan_Height": 0
          },
          "gathering_FanInfo": {
            "fan_StartAngle": 0,
            "fan_EndAngle": 0,
            "fan_DistanceMin": 1,
            "fan_DistanceMax": 3,
            "fan_Height": 0
          },
          "useSpecificWalkingSpots": false,
          "walkablePositions": []
        }
      ]
    }
  ],
  "groupCount": 3,
  "requiresFolklore": false,
  "folkloreBook": null,
  "author": null,
  "lastUpdated": null,
  "timedNode": false
}