{
  "routeId": 287,
  "territoryId": 398,
  "zoneName": "The Dravanian Forelands",
  "placeName": "The Smoldering Wastes",
  "expansionId": 1,
  "gatheringJobId": 16,
  "levelRequirement": 55,
  "nodeIds": [
    31332,
    31333,
    31328,
    31329,
    31330,
    31331
  ],
  "requiresFolklore": false,
  "folkloreBook": "",
  "author": "alydev",
  "lastUpdated": "2025-12-08",
  "nodeGroups": [
    {
      "groupId": 0,
      "nodes": [
        {
          "nodeId": 31332,
          "locations": [
            {
              "position": {
                "x": 328.7086,
                "y": -102.6966,
                "z": 475.8608
              },
              "minAngle": 170,
              "maxAngle": 245,
              "minDistance": 1,
              "maxDistance": 5,
              "fanHightIncrease": 0,
              "allowFlying": true,
              "specificWalkSpots": false,
              "walkablePositions": [],
              "gatherAngle_Minimum": 0,
              "gatherAngle_Maximum": 0,
              "gatherDistance_Minimum": 1,
              "gatherDistance_Maximum": 2.4,
              "gatherFan_Height": 0
            }
          ]
        },
        {
          "nodeId": 31333,
          "locations": [
            {
              "position": {
                "x": 314.1694,
                "y": -105.883,
                "z": 493.588
              },
              "minAngle": 75,
              "maxAngle": 195,
              "minDistance": 1,
              "maxDistance": 5,
              "fanHightIncrease": 0,
              "allowFlying": true,
              "specificWalkSpots": false,
              "walkablePositions": [],
              "gatherAngle_Minimum": 0,
              "gatherAngle_Maximum": 0,
              "gatherDistance_Minimum": 1,
              "gatherDistance_Maximum": 2.4,
              "gatherFan_Height": 0
            },
            {
              "position": {
                "x": 321.6429,
                "y": -107.4091,
                "z": 514.6582
              },
              "minAngle": 10,
              "maxAngle": 95,
              "minDistance": 1,
              "maxDistance": 5,
              "fanHightIncrease": 0,
              "allowFlying": true,
              "specificWalkSpots": false,
              "walkablePositions": [],
              "gatherAngle_Minimum": 0,
              "gatherAngle_Maximum": 0,
              "gatherDistance_Minimum": 1,
              "gatherDistance_Maximum": 2.4,
              "gatherFan_Height": 0
            },
            {
              "position": {
                "x": 350.9794,
                "y": -99.78679,
                "z": 477.761
              },
              "minAngle": 140,
              "maxAngle": 240,
              "minDistance": 1,
              "maxDistance": 5,
              "fanHightIncrease": 0,
              "allowFlying": true,
              "specificWalkSpots": false,
              "walkablePositions": [],
              "gatherAngle_Minimum": 0,
              "gatherAngle_Maximum": 0,
              "gatherDistance_Minimum": 1,
              "gatherDistance_Maximum": 2.4,
              "gatherFan_Height": 0
            }
          ]
        }
      ]
    },
    {
      "groupId": 1,
      "nodes": [
        {
          "nodeId": 31328,
          "locations": [
            {
              "position": {
                "x": 263.9153,
                "y": -105.3216,
                "z": 380.818
              },
              "minAngle": 310,
              "maxAngle": 55,
              "minDistance": 1,
              "maxDistance": 5,
              "fanHightIncrease": 0,
              "allowFlying": true,
              "specificWalkSpots": false,
              "walkablePositions": [],
              "gatherAngle_Minimum": 0,
              "gatherAngle_Maximum": 0,
              "gatherDistance_Minimum": 1,
              "gatherDistance_Maximum": 2.4,
              "gatherFan_Height": 0
            }
          ]
        },
        {
          "nodeId": 31329,
          "locations": [
            {
              "position": {
                "x": 240.4443,
                "y": -107.8556,
                "z": 393.5267
              },
              "minAngle": 300,
              "maxAngle": 0,
              "minDistance": 1,
              "maxDistance": 5,
              "fanHightIncrease": 0,
              "allowFlying": true,
              "specificWalkSpots": false,
              "walkablePositions": [],
              "gatherAngle_Minimum": 0,
              "gatherAngle_Maximum": 0,
              "gatherDistance_Minimum": 1,
              "gatherDistance_Maximum": 2.4,
              "gatherFan_Height": 0
            },
            {
              "position": {
                "x": 274.7044,
                "y": -105.9449,
                "z": 375.312
              },
              "minAngle": 310,
              "maxAngle": 0,
              "minDistance": 1,
              "maxDistance": 5,
              "fanHightIncrease": 0,
              "allowFlying": true,
              "specificWalkSpots": false,
              "walkablePositions": [],
              "gatherAngle_Minimum": 0,
              "gatherAngle_Maximum": 0,
              "gatherDistance_Minimum": 1,
              "gatherDistance_Maximum": 2.4,
              "gatherFan_Height": 0
            },
            {
              "position": {
                "x": 288.4626,
                "y": -101.6914,
                "z": 344.4234
              },
              "minAngle": 200,
              "maxAngle": 305,
              "minDistance": 1,
              "maxDistance": 5,
              "fanHightIncrease": 0,
              "allowFlying": true,
              "specificWalkSpots": false,
              "walkablePositions": [],
              "gatherAngle_Minimum": 0,
              "gatherAngle_Maximum": 0,
              "gatherDistance_Minimum": 1,
              "gatherDistance_Maximum": 2.4,
              "gatherFan_Height": 0
            }
          ]
        },
        {
          "nodeId": 31330,
          "locations": [
            {
              "position": {
                "x": 136.9452,
                "y": -122.3492,
                "z": 508.8448
              },
              "minAngle": 135,
              "maxAngle": 235,
              "minDistance": 1,
              "maxDistance": 5,
              "fanHightIncrease": 0,
              "allowFlying": true,
              "specificWalkSpots": false,
              "walkablePositions": [],
              "gatherAngle_Minimum": 0,
              "gatherAngle_Maximum": 0,
              "gatherDistance_Minimum": 1,
              "gatherDistance_Maximum": 2.4,
              "gatherFan_Height": 0
            }
          ]
        },
        {
          "nodeId": 31331,
          "locations": [
            {
              "position": {
                "x": 124.674,
                "y": -121.94,
                "z": 519.6763
              },
              "minAngle": 260,
              "maxAngle": 0,
              "minDistance": 1,
              "maxDistance": 5,
              "fanHightIncrease": 0,
              "allowFlying": true,
              "specificWalkSpots": false,
              "walkablePositions": [],
              "gatherAngle_Minimum": 0,
              "gatherAngle_Maximum": 0,
              "gatherDistance_Minimum": 1,
              "gatherDistance_Maximum": 2.4,
              "gatherFan_Height": 0
            },
            {
              "position": {
                "x": 148.088,
                "y": -119.1193,
                "z": 550.0385
              },
              "minAngle": 20,
              "maxAngle": 120,
              "minDistance": 1,
              "maxDistance": 5,
              "fanHightIncrease": 0,
              "allowFlying": true,
              "specificWalkSpots": false,
              "walkablePositions": [],
              "gatherAngle_Minimum": 0,
              "gatherAngle_Maximum": 0,
              "gatherDistance_Minimum": 1,
              "gatherDistance_Maximum": 2.4,
              "gatherFan_Height": 0
            },
            {
              "position": {
                "x": 163.5542,
                "y": -118.4263,
                "z": 532.9957
              },
              "minAngle": 170,
              "maxAngle": 240,
              "minDistance": 1.4,
              "maxDistance": 3,
              "fanHightIncrease": 0,
              "allowFlying": true,
              "specificWalkSpots": false,
              "walkablePositions": [],
              "gatherAngle_Minimum": 0,
              "gatherAngle_Maximum": 0,
              "gatherDistance_Minimum": 1,
              "gatherDistance_Maximum": 2.4,
              "gatherFan_Height": 0
            }
          ]
        }
      ]
    }
  ],
  "timedNode": false
}