{
  "routeId": 609,
  "territoryId": 816,
  "zoneName": "Il Mheg",
  "placeName": "Saint Fathric\u0027s Temple",
  "expansionId": 3,
  "gatheringJobId": 16,
  "levelRequirement": 80,
  "nodeIds": [
    32683
  ],
  "requiresFolklore": false,
  "folkloreBook": "",
  "author": "alydev",
  "lastUpdated": "2025-12-08",
  "nodeGroups": [
    {
      "groupId": 0,
      "nodes": [
        {
          "nodeId": 32683,
          "locations": [
            {
              "position": {
                "x": 427.9646,
                "y": 183.3215,
                "z": -56.99644
              },
              "minAngle": 320,
              "maxAngle": 0,
              "minDistance": 1,
              "maxDistance": 5,
              "fanHightIncrease": 0,
              "allowFlying": true,
              "specificWalkSpots": false,
              "walkablePositions": [],
              "gatherAngle_Minimum": 0,
              "gatherAngle_Maximum": 0,
              "gatherDistance_Minimum": 1,
              "gatherDistance_Maximum": 2.4,
              "gatherFan_Height": 0
            },
            {
              "position": {
                "x": 459.9862,
                "y": 186.8991,
                "z": -60.42558
              },
              "minAngle": -0,
              "maxAngle": 80,
              "minDistance": 1,
              "maxDistance": 5,
              "fanHightIncrease": 0,
              "allowFlying": true,
              "specificWalkSpots": false,
              "walkablePositions": [],
              "gatherAngle_Minimum": 0,
              "gatherAngle_Maximum": 0,
              "gatherDistance_Minimum": 1,
              "gatherDistance_Maximum": 2.4,
              "gatherFan_Height": 0
            },
            {
              "position": {
                "x": 475.3741,
                "y": 192.514,
                "z": -15.59578
              },
              "minAngle": 35,
              "maxAngle": 110,
              "minDistance": 1,
              "maxDistance": 5,
              "fanHightIncrease": 0,
              "allowFlying": true,
              "specificWalkSpots": false,
              "walkablePositions": [],
              "gatherAngle_Minimum": 0,
              "gatherAngle_Maximum": 0,
              "gatherDistance_Minimum": 1,
              "gatherDistance_Maximum": 2.4,
              "gatherFan_Height": 0
            }
          ]
        }
      ]
    }
  ],
  "timedNode": false
}