{
  "routeId": 678,
  "territoryId": 816,
  "zoneName": "Il Mheg",
  "placeName": "Good Jenanna\u0027s Grace",
  "expansionId": 3,
  "gatheringJobId": 16,
  "levelRequirement": 75,
  "nodeIds": [
    32971,
    32972,
    32973,
    32974,
    32975,
    32976
  ],
  "requiresFolklore": false,
  "folkloreBook": "",
  "author": "Ice",
  "lastUpdated": "2025-12-27",
  "nodeGroups": [
    {
      "groupId": 0,
      "nodes": [
        {
          "nodeId": 32971,
          "locations": [
            {
              "position": {
                "x": 0,
                "y": 0,
                "z": 0
              },
              "minAngle": -180,
              "maxAngle": 180,
              "minDistance": 1,
              "maxDistance": 111,
              "allowFlying": true,
              "fanHightIncrease": 0
            }
          ]
        },
        {
          "nodeId": 32972,
          "locations": [
            {
              "position": {
                "x": 0,
                "y": 0,
                "z": 0
              },
              "minAngle": -180,
              "maxAngle": 180,
              "minDistance": 1,
              "maxDistance": 111,
              "allowFlying": true,
              "fanHightIncrease": 0
            }
          ]
        },
        {
          "nodeId": 32973,
          "locations": [
            {
              "position": {
                "x": 0,
                "y": 0,
                "z": 0
              },
              "minAngle": -180,
              "maxAngle": 180,
              "minDistance": 1,
              "maxDistance": 111,
              "allowFlying": true,
              "fanHightIncrease": 0
            }
          ]
        },
        {
          "nodeId": 32974,
          "locations": [
            {
              "position": {
                "x": 0,
                "y": 0,
                "z": 0
              },
              "minAngle": -180,
              "maxAngle": 180,
              "minDistance": 1,
              "maxDistance": 111,
              "allowFlying": true,
              "fanHightIncrease": 0
            }
          ]
        },
        {
          "nodeId": 32975,
          "locations": [
            {
              "position": {
                "x": 0,
                "y": 0,
                "z": 0
              },
              "minAngle": -180,
              "maxAngle": 180,
              "minDistance": 1,
              "maxDistance": 111,
              "allowFlying": true,
              "fanHightIncrease": 0
            }
          ]
        },
        {
          "nodeId": 32976,
          "locations": [
            {
              "position": {
                "x": 0,
                "y": 0,
                "z": 0
              },
              "minAngle": -180,
              "maxAngle": 180,
              "minDistance": 1,
              "maxDistance": 111,
              "allowFlying": true,
              "fanHightIncrease": 0
            }
          ]
        }
      ]
    }
  ],
  "timedNode": false
}