{
  "routeId": 677,
  "territoryId": 818,
  "zoneName": "The Tempest",
  "placeName": "Walls of the Forgotten",
  "expansionId": 3,
  "gatheringJobId": 16,
  "levelRequirement": 1,
  "nodeIds": [
    32965,
    32966,
    32967,
    32968,
    32969,
    32970
  ],
  "nodeGroups": [
    {
      "groupId": 0,
      "nodes": [
        {
          "nodeId": 32965,
          "locations": [
            {
              "position": {},
              "allowFlying": true,
              "flight_FanInfo": {
                "fan_StartAngle": 0,
                "fan_EndAngle": 0,
                "fan_DistanceMin": 1,
                "fan_DistanceMax": 3,
                "fan_Height": 0
              },
              "gathering_FanInfo": {
                "fan_StartAngle": 0,
                "fan_EndAngle": 0,
                "fan_DistanceMin": 1,
                "fan_DistanceMax": 3,
                "fan_Height": 0
              },
              "useSpecificWalkingSpots": false,
              "walkablePositions": []
            }
          ]
        },
        {
          "nodeId": 32966,
          "locations": [
            {
              "position": {},
              "allowFlying": true,
              "flight_FanInfo": {
                "fan_StartAngle": 0,
                "fan_EndAngle": 0,
                "fan_DistanceMin": 1,
                "fan_DistanceMax": 3,
                "fan_Height": 0
              },
              "gathering_FanInfo": {
                "fan_StartAngle": 0,
                "fan_EndAngle": 0,
                "fan_DistanceMin": 1,
                "fan_DistanceMax": 3,
                "fan_Height": 0
              },
              "useSpecificWalkingSpots": false,
              "walkablePositions": []
            }
          ]
        },
        {
          "nodeId": 32967,
          "locations": [
            {
              "position": {},
              "allowFlying": true,
              "flight_FanInfo": {
                "fan_StartAngle": 0,
                "fan_EndAngle": 0,
                "fan_DistanceMin": 1,
                "fan_DistanceMax": 3,
                "fan_Height": 0
              },
              "gathering_FanInfo": {
                "fan_StartAngle": 0,
                "fan_EndAngle": 0,
                "fan_DistanceMin": 1,
                "fan_DistanceMax": 3,
                "fan_Height": 0
              },
              "useSpecificWalkingSpots": false,
              "walkablePositions": []
            }
          ]
        },
        {
          "nodeId": 32968,
          "locations": [
            {
              "position": {},
              "allowFlying": true,
              "flight_FanInfo": {
                "fan_StartAngle": 0,
                "fan_EndAngle": 0,
                "fan_DistanceMin": 1,
                "fan_DistanceMax": 3,
                "fan_Height": 0
              },
              "gathering_FanInfo": {
                "fan_StartAngle": 0,
                "fan_EndAngle": 0,
                "fan_DistanceMin": 1,
                "fan_DistanceMax": 3,
                "fan_Height": 0
              },
              "useSpecificWalkingSpots": false,
              "walkablePositions": []
            }
          ]
        },
        {
          "nodeId": 32969,
          "locations": [
            {
              "position": {},
              "allowFlying": true,
              "flight_FanInfo": {
                "fan_StartAngle": 0,
                "fan_EndAngle": 0,
                "fan_DistanceMin": 1,
                "fan_DistanceMax": 3,
                "fan_Height": 0
              },
              "gathering_FanInfo": {
                "fan_StartAngle": 0,
                "fan_EndAngle": 0,
                "fan_DistanceMin": 1,
                "fan_DistanceMax": 3,
                "fan_Height": 0
              },
              "useSpecificWalkingSpots": false,
              "walkablePositions": []
            }
          ]
        },
        {
          "nodeId": 32970,
          "locations": [
            {
              "position": {},
              "allowFlying": true,
              "flight_FanInfo": {
                "fan_StartAngle": 0,
                "fan_EndAngle": 0,
                "fan_DistanceMin": 1,
                "fan_DistanceMax": 3,
                "fan_Height": 0
              },
              "gathering_FanInfo": {
                "fan_StartAngle": 0,
                "fan_EndAngle": 0,
                "fan_DistanceMin": 1,
                "fan_DistanceMax": 3,
                "fan_Height": 0
              },
              "useSpecificWalkingSpots": false,
              "walkablePositions": []
            }
          ]
        }
      ]
    }
  ],
  "requiresFolklore": false,
  "folkloreBook": "",
  "author": "Ice",
  "lastUpdated": "2025-12-29 18:24:41",
  "timedNode": false
}