{
  "routeId": 245,
  "territoryId": 148,
  "zoneName": "Central Shroud",
  "placeName": "Greentear",
  "expansionId": 0,
  "gatheringJobId": 17,
  "levelRequirement": 50,
  "nodeIds": [
    31053
  ],
  "requiresFolklore": false,
  "folkloreBook": "",
  "author": "Ice",
  "lastUpdated": "2025-12-08",
  "nodeGroups": [
    {
      "groupId": 0,
      "nodes": [
        {
          "nodeId": 31053,
          "locations": [
            {
              "position": {
                "x": 440.3295,
                "y": 31.85231,
                "z": -14.63871
              },
              "minAngle": 140,
              "maxAngle": 280,
              "minDistance": 1,
              "maxDistance": 5,
              "allowFlying": true
            },
            {
              "position": {
                "x": 468.1901,
                "y": 24.69732,
                "z": -113.0331
              },
              "minAngle": -85,
              "maxAngle": 45,
              "minDistance": 1,
              "maxDistance": 5,
              "allowFlying": true
            },
            {
              "position": {
                "x": 453.4795,
                "y": 19.32409,
                "z": -70.09693
              },
              "minAngle": 160,
              "maxAngle": 275,
              "minDistance": 1,
              "maxDistance": 5,
              "allowFlying": true
            }
          ]
        }
      ]
    }
  ]
}