{
  "routeId": 999,
  "territoryId": 1190,
  "zoneName": "Shaaloani",
  "placeName": "Yawtanane Grasslands",
  "expansionId": 5,
  "gatheringJobId": 17,
  "levelRequirement": 95,
  "nodeIds": [
    34899,
    34900,
    34901,
    34902,
    34903,
    34904
  ],
  "nodeInfo": [
    {
      "groupId": 0,
      "nodeId": 34903,
      "locations": [
        {
          "position": {
            "x": 530.04,
            "y": 6.585761,
            "z": 243.3026
          },
          "allowFlying": true,
          "flight_FanInfo": {
            "fan_StartAngle": 0,
            "fan_EndAngle": 359,
            "fan_DistanceMin": 2.5,
            "fan_DistanceMax": 4,
            "fan_Height": 0.26
          },
          "gathering_FanInfo": {
            "fan_StartAngle": 0,
            "fan_EndAngle": 359,
            "fan_DistanceMin": 1,
            "fan_DistanceMax": 2,
            "fan_Height": 0
          },
          "useSpecificWalkingSpots": false,
          "walkablePositions": []
        }
      ]
    },
    {
      "groupId": 0,
      "nodeId": 34904,
      "locations": [
        {
          "position": {
            "x": 510.6736,
            "y": 5.43621,
            "z": 247.2418
          },
          "allowFlying": true,
          "flight_FanInfo": {
            "fan_StartAngle": 35,
            "fan_EndAngle": 247,
            "fan_DistanceMin": 2.5,
            "fan_DistanceMax": 4,
            "fan_Height": 0.23
          },
          "gathering_FanInfo": {
            "fan_StartAngle": 0,
            "fan_EndAngle": 359,
            "fan_DistanceMin": 1,
            "fan_DistanceMax": 2,
            "fan_Height": 0
          },
          "useSpecificWalkingSpots": false,
          "walkablePositions": []
        },
        {
          "position": {
            "x": 537.3219,
            "y": 6.59951,
            "z": 234.4762
          },
          "allowFlying": true,
          "flight_FanInfo": {
            "fan_StartAngle": 0,
            "fan_EndAngle": 359,
            "fan_DistanceMin": 2.5,
            "fan_DistanceMax": 4,
            "fan_Height": 0.41
          },
          "gathering_FanInfo": {
            "fan_StartAngle": 0,
            "fan_EndAngle": 359,
            "fan_DistanceMin": 1,
            "fan_DistanceMax": 2,
            "fan_Height": 0
          },
          "useSpecificWalkingSpots": false,
          "walkablePositions": []
        },
        {
          "position": {
            "x": 534.63,
            "y": 7.40439,
            "z": 261.0851
          },
          "allowFlying": true,
          "flight_FanInfo": {
            "fan_StartAngle": 0,
            "fan_EndAngle": 359,
            "fan_DistanceMin": 2.5,
            "fan_DistanceMax": 4,
            "fan_Height": 0.23
          },
          "gathering_FanInfo": {
            "fan_StartAngle": 0,
            "fan_EndAngle": 359,
            "fan_DistanceMin": 1,
            "fan_DistanceMax": 2,
            "fan_Height": 0
          },
          "useSpecificWalkingSpots": false,
          "walkablePositions": []
        }
      ]
    },
    {
      "groupId": 1,
      "nodeId": 34901,
      "locations": [
        {
          "position": {
            "x": 343.0447,
            "y": 0.1167868,
            "z": 146.4354
          },
          "allowFlying": true,
          "flight_FanInfo": {
            "fan_StartAngle": 0,
            "fan_EndAngle": 359,
            "fan_DistanceMin": 2.5,
            "fan_DistanceMax": 4,
            "fan_Height": 0.39
          },
          "gathering_FanInfo": {
            "fan_StartAngle": 0,
            "fan_EndAngle": 359,
            "fan_DistanceMin": 1,
            "fan_DistanceMax": 2,
            "fan_Height": 0
          },
          "useSpecificWalkingSpots": false,
          "walkablePositions": []
        }
      ]
    },
    {
      "groupId": 1,
      "nodeId": 34902,
      "locations": [
        {
          "position": {
            "x": 349.9641,
            "y": 2.9944,
            "z": 166.7519
          },
          "allowFlying": true,
          "flight_FanInfo": {
            "fan_StartAngle": 0,
            "fan_EndAngle": 359,
            "fan_DistanceMin": 2.5,
            "fan_DistanceMax": 4,
            "fan_Height": 0.31
          },
          "gathering_FanInfo": {
            "fan_StartAngle": 0,
            "fan_EndAngle": 359,
            "fan_DistanceMin": 1,
            "fan_DistanceMax": 2,
            "fan_Height": 0
          },
          "useSpecificWalkingSpots": false,
          "walkablePositions": []
        },
        {
          "position": {
            "x": 358.951,
            "y": 1.226612,
            "z": 152.3553
          },
          "allowFlying": true,
          "flight_FanInfo": {
            "fan_StartAngle": 0,
            "fan_EndAngle": 359,
            "fan_DistanceMin": 2.5,
            "fan_DistanceMax": 4,
            "fan_Height": 0.55
          },
          "gathering_FanInfo": {
            "fan_StartAngle": 0,
            "fan_EndAngle": 359,
            "fan_DistanceMin": 1,
            "fan_DistanceMax": 2,
            "fan_Height": 0.31
          },
          "useSpecificWalkingSpots": false,
          "walkablePositions": []
        },
        {
          "position": {
            "x": 350.1042,
            "y": -2.02238,
            "z": 133.0248
          },
          "allowFlying": true,
          "flight_FanInfo": {
            "fan_StartAngle": 0,
            "fan_EndAngle": 359,
            "fan_DistanceMin": 2.5,
            "fan_DistanceMax": 4,
            "fan_Height": 1.12
          },
          "gathering_FanInfo": {
            "fan_StartAngle": 0,
            "fan_EndAngle": 359,
            "fan_DistanceMin": 1,
            "fan_DistanceMax": 2,
            "fan_Height": 0.71
          },
          "useSpecificWalkingSpots": false,
          "walkablePositions": []
        }
      ]
    },
    {
      "groupId": 2,
      "nodeId": 34899,
      "locations": [
        {
          "position": {
            "x": 578.6227,
            "y": 5.976591,
            "z": 76.53668
          },
          "allowFlying": true,
          "flight_FanInfo": {
            "fan_StartAngle": 0,
            "fan_EndAngle": 359,
            "fan_DistanceMin": 2.5,
            "fan_DistanceMax": 4,
            "fan_Height": 0.94
          },
          "gathering_FanInfo": {
            "fan_StartAngle": 0,
            "fan_EndAngle": 359,
            "fan_DistanceMin": 1,
            "fan_DistanceMax": 2,
            "fan_Height": 0.64
          },
          "useSpecificWalkingSpots": false,
          "walkablePositions": []
        }
      ]
    },
    {
      "groupId": 2,
      "nodeId": 34900,
      "locations": [
        {
          "position": {
            "x": 571.4374,
            "y": 5.934396,
            "z": 93.85439
          },
          "allowFlying": true,
          "flight_FanInfo": {
            "fan_StartAngle": 0,
            "fan_EndAngle": 359,
            "fan_DistanceMin": 2.5,
            "fan_DistanceMax": 4,
            "fan_Height": 1.15
          },
          "gathering_FanInfo": {
            "fan_StartAngle": 0,
            "fan_EndAngle": 359,
            "fan_DistanceMin": 1,
            "fan_DistanceMax": 2,
            "fan_Height": 0.69
          },
          "useSpecificWalkingSpots": false,
          "walkablePositions": []
        },
        {
          "position": {
            "x": 580.9511,
            "y": 4.927295,
            "z": 64.64209
          },
          "allowFlying": true,
          "flight_FanInfo": {
            "fan_StartAngle": 0,
            "fan_EndAngle": 359,
            "fan_DistanceMin": 2.5,
            "fan_DistanceMax": 4,
            "fan_Height": 1.02
          },
          "gathering_FanInfo": {
            "fan_StartAngle": 0,
            "fan_EndAngle": 359,
            "fan_DistanceMin": 1,
            "fan_DistanceMax": 2,
            "fan_Height": 0.8
          },
          "useSpecificWalkingSpots": false,
          "walkablePositions": []
        },
        {
          "position": {
            "x": 595.0986,
            "y": 9.620093,
            "z": 81.96783
          },
          "allowFlying": true,
          "flight_FanInfo": {
            "fan_StartAngle": 0,
            "fan_EndAngle": 359,
            "fan_DistanceMin": 2.5,
            "fan_DistanceMax": 4,
            "fan_Height": 1.45
          },
          "gathering_FanInfo": {
            "fan_StartAngle": 0,
            "fan_EndAngle": 359,
            "fan_DistanceMin": 1,
            "fan_DistanceMax": 2,
            "fan_Height": 0.73
          },
          "useSpecificWalkingSpots": false,
          "walkablePositions": []
        }
      ]
    }
  ],
  "groupCount": 3,
  "requiresFolklore": false,
  "folkloreBook": "",
  "author": "liza, Ice",
  "lastUpdated": "2025-12-26 23:22:24",
  "timedNode": false
}